dyntapy/__init__.py
dyntapy/_context.py
dyntapy/assignments.py
dyntapy/csr.py
dyntapy/demand.py
dyntapy/demand_data.py
dyntapy/graph_utils.py
dyntapy/results.py
dyntapy/settings.py
dyntapy/supply.py
dyntapy/supply_data.py
dyntapy/utilities.py
dyntapy/visualization.py
dyntapy/dta/__init__.py
dyntapy/dta/aon.py
dyntapy/dta/debugging.py
dyntapy/dta/deterministic.py
dyntapy/dta/dynamic_dijkstra.py
dyntapy/dta/i_ltm.py
dyntapy/dta/i_ltm_aon.py
dyntapy/dta/i_ltm_cls.py
dyntapy/dta/i_ltm_setup.py
dyntapy/dta/incremental_assignment.py
dyntapy/dta/orca_nodel_model.py
dyntapy/dta/qr_projection.py
dyntapy/dta/travel_times.py
dyntapy/sta/__init__.py
dyntapy/sta/_debugging_sta.py
dyntapy/sta/dial_b.py
dyntapy/sta/dial_stochastic_assignment.py
dyntapy/sta/equilibrate_bush.py
dyntapy/sta/gap.py
dyntapy/sta/msa.py
dyntapy/sta/uncongested_dial.py
dyntapy/sta/utilities.py
dyntapy/toy_networks/birmingham_net.tntp
dyntapy/toy_networks/birmingham_node.tntp
dyntapy/toy_networks/chicagoregional_net.tntp
dyntapy/toy_networks/chicagoregional_node.tntp
dyntapy/toy_networks/chicagosketch_net.tntp
dyntapy/toy_networks/chicagosketch_node.tntp
dyntapy/toy_networks/siouxfalls_net.tntp
dyntapy/toy_networks/siouxfalls_node.tntp
dyntapy-0.2.4.dist-info/LICENSE.txt
dyntapy-0.2.4.dist-info/METADATA
dyntapy-0.2.4.dist-info/WHEEL
dyntapy-0.2.4.dist-info/top_level.txt
dyntapy-0.2.4.dist-info/RECORD
