Metadata-Version: 2.1
Name: dyntapy
Version: 0.2.4
Summary: Macroscopic Static and Dynamic Traffic Assignment in Python 
Home-page: https://gitlab.kuleuven.be/ITSCreaLab/public-toolboxes/dyntapy
Author: Paul Ortmann
Author-email: itscrealab@kuleuven.be
License: GPLv3
Platform: any
Classifier: Development Status :: 3 - Alpha
Classifier: License :: OSI Approved :: GNU General Public License v3 (GPLv3)
Classifier: Operating System :: OS Independent
Classifier: Intended Audience :: Science/Research
Classifier: Topic :: Scientific/Engineering :: Physics
Classifier: Topic :: Scientific/Engineering :: Mathematics
Classifier: Topic :: Scientific/Engineering :: Information Analysis
Classifier: Programming Language :: Python
Classifier: Programming Language :: Python :: 3
Classifier: Programming Language :: Python :: 3.9
Requires-Python: >=3.9
License-File: LICENSE.txt
Requires-Dist: numba
Requires-Dist: bokeh
Requires-Dist: osmnx
Requires-Dist: pandas
Requires-Dist: scipy
Requires-Dist: numpy
Requires-Dist: geojson
Requires-Dist: pyyaml
Requires-Dist: networkx
Requires-Dist: pyproj
Requires-Dist: geopandas
Requires-Dist: Shapely
Requires-Dist: matplotlib
Requires-Dist: notebook
Requires-Dist: setuptools
